pyrenoweb/__init__.py
pyrenoweb/api.py
pyrenoweb/const.py
pyrenoweb/data.py
pyrenoweb/images.py
pyrenoweb-2.0.17.dist-info/LICENSE
pyrenoweb-2.0.17.dist-info/METADATA
pyrenoweb-2.0.17.dist-info/WHEEL
pyrenoweb-2.0.17.dist-info/top_level.txt
pyrenoweb-2.0.17.dist-info/RECORD
