Metadata-Version: 2.1
Name: pyrenoweb
Version: 2.0.17
Summary: Gets garbage collection data from RenoWeb
Home-page: https://github.com/briis/pyrenoweb
Author: briis
Author-email: bjarne@briis.com
License: MIT
Classifier: Programming Language :: Python :: 3
Classifier: License :: OSI Approved :: MIT License
Classifier: Operating System :: OS Independent
Classifier: Development Status :: 4 - Beta
License-File: LICENSE
